impermium
